{
  "generated_at": "2026-07-09T09:50:33Z",
  "leaderboard": [
    {
      "participant_alias": "sharp-fortress",
      "total_score": 55,
      "latest_time": "2026-07-09T09:40:27.675752979Z",
      "repos": [
        "verademo-javascript-api"
      ],
      "rank": 1
    },
    {
      "participant_alias": "vigilant-keeper",
      "total_score": 55,
      "latest_time": "2026-07-09T09:43:37.463538213Z",
      "repos": [
        "verademo-javascript-api"
      ],
      "rank": 2
    },
    {
      "participant_alias": "fierce-knight",
      "total_score": 55,
      "latest_time": "2026-07-09T09:49:56.195710471Z",
      "repos": [
        "verademo-javascript-api"
      ],
      "rank": 3
    },
    {
      "participant_alias": "vivid-dragon",
      "total_score": 54,
      "latest_time": "2026-07-09T09:49:52.625412328Z",
      "repos": [
        "verademo-javascript-api"
      ],
      "rank": 4
    },
    {
      "participant_alias": "dashing-keeper",
      "total_score": 0,
      "latest_time": "2026-07-09T09:50:23.028384373Z",
      "repos": [
        "verademo-javascript-api"
      ],
      "rank": 5
    }
  ]
}